throttle_it/__init__.py
throttle_it-0.1.0.dist-info/METADATA
throttle_it-0.1.0.dist-info/WHEEL
throttle_it-0.1.0.dist-info/licenses/LICENSE
throttle_it-0.1.0.dist-info/RECORD
