Metadata-Version: 2.4
Name: throttle-it
Version: 0.1.0
Summary: Throttle your API calls
License-File: LICENSE
Requires-Python: >=3.10
Requires-Dist: pyrate-limiter>=3.9.0
Requires-Dist: requests<2.32.5
